recvani/__init__.py
recvani/rv_client.py
recvani/rv_requests.py
recvani/example/__init__.py
recvani/example/api_call.py
recvani/example/config.py
recvani/example/csv_sender.py
recvani/requests/__init__.py
recvani/requests/requests.py
recvani-0.0.8.dist-info/LICENSE
recvani-0.0.8.dist-info/METADATA
recvani-0.0.8.dist-info/WHEEL
recvani-0.0.8.dist-info/top_level.txt
recvani-0.0.8.dist-info/RECORD
